ashare_data/__init__.py
ashare_data/cli.py
ashare_data/utils/DailyDataReader.py
ashare_data/utils/KLineFetcher_EM.py
ashare_data/utils/ParquetDailyStore.py
ashare_data/utils/__init__.py
ashare_data-0.5.0.dist-info/METADATA
ashare_data-0.5.0.dist-info/WHEEL
ashare_data-0.5.0.dist-info/entry_points.txt
ashare_data-0.5.0.dist-info/RECORD
