Metadata-Version: 2.4
Name: ashare-data
Version: 0.5.0
Summary: A command-line tool for A-share market data management.
Author-email: zw <szzend@qq.com>
Requires-Python: >=3.13
Requires-Dist: akshare>=1.16.73
Requires-Dist: click>=8.1.8
Requires-Dist: pandas>=2.2.3
Requires-Dist: pyarrow>=19.0.1
